algorithms/__init__.py
algorithms/model.py
algorithms/naive/__init__.py
algorithms/naive/random_model.py
algorithms/qsom/__init__.py
algorithms/qsom/qsom.py
algorithms/qsom/qsom_agent.py
algorithms/qsom/som.py
algorithms/util/__init__.py
algorithms/util/action_perturbator.py
algorithms/util/action_selector.py
smartgrid/data/openei/Readme.md
smartgrid/data/openei/profile_office_annually.npz
smartgrid/data/openei/profile_office_daily.npz
smartgrid/data/openei/profile_residential_annually.npz
smartgrid/data/openei/profile_residential_daily.npz
smartgrid/data/openei/profile_school_annually.npz
smartgrid/data/openei/profile_school_daily.npz
smartgrid/__init__.py
smartgrid/environment.py
smartgrid/make_env.py
smartgrid/scenarii.py
smartgrid/world.py
smartgrid/agents/__init__.py
smartgrid/agents/agent.py
smartgrid/agents/data_conversion.py
smartgrid/agents/profile/__init__.py
smartgrid/agents/profile/agent_profile.py
smartgrid/agents/profile/comfort.py
smartgrid/agents/profile/need.py
smartgrid/agents/profile/production.py
smartgrid/observation/__init__.py
smartgrid/observation/base_observation.py
smartgrid/observation/global_observation.py
smartgrid/observation/local_observation.py
smartgrid/observation/observation_manager.py
smartgrid/rewards/__init__.py
smartgrid/rewards/reward.py
smartgrid/rewards/reward_collection.py
smartgrid/rewards/reward_constraints.py
smartgrid/rewards/argumentation/__init__.py
smartgrid/rewards/argumentation/affordability.py
smartgrid/rewards/argumentation/env_sustain.py
smartgrid/rewards/argumentation/inclusiveness.py
smartgrid/rewards/argumentation/situation.py
smartgrid/rewards/argumentation/supply_security.py
smartgrid/rewards/numeric/__init__.py
smartgrid/rewards/numeric/differentiated/__init__.py
smartgrid/rewards/numeric/differentiated/adaptability.py
smartgrid/rewards/numeric/differentiated/equity.py
smartgrid/rewards/numeric/differentiated/multi_objective_product.py
smartgrid/rewards/numeric/differentiated/multi_objective_sum.py
ethical_smart_grid-2.0.0.dist-info/METADATA
ethical_smart_grid-2.0.0.dist-info/WHEEL
ethical_smart_grid-2.0.0.dist-info/licenses/LICENSE.md
ethical_smart_grid-2.0.0.dist-info/RECORD
