Metadata-Version: 2.3
Name: ethical-smart-grid
Version: 2.0.0
Summary: A RL environment for learning ethically-aligned behaviours in a Smart Grid simulator.
Project-URL: Source code, https://github.com/ethicsai/ethical-smart-grid
Project-URL: Bug Tracker, https://github.com/ethicsai/ethical-smart-grid/issues
Project-URL: Documentation, https://ethicsai.github.io/ethical-smart-grid/
Author-email: Clément Scheirlinck <clement.scheirlinck@etu.univ-lyon1.fr>
Maintainer-email: Rémy Chaput <rchaput.pro@gmail.com>
License: MIT License
License-File: LICENSE.md
Keywords: Gym,Gymnasium,Machine Ethics,Multi-Agent System,OpenAI Gym,Reinforcement Learning,Smart Grid
Classifier: Intended Audience :: Science/Research
Classifier: License :: OSI Approved :: MIT License
Classifier: Operating System :: OS Independent
Classifier: Programming Language :: Python :: 3
Classifier: Programming Language :: Python :: 3.7
Classifier: Programming Language :: Python :: 3.8
Classifier: Programming Language :: Python :: 3.9
Classifier: Programming Language :: Python :: 3.10
Classifier: Programming Language :: Python :: 3.11
Classifier: Programming Language :: Python :: 3.12
Classifier: Topic :: Scientific/Engineering :: Artificial Intelligence
Requires-Python: >=3.7
Requires-Dist: gymnasium>=0.26.3
Requires-Dist: numpy>=1.19.0
Requires-Dist: pettingzoo>=1.22.3
Provides-Extra: extra
Requires-Dist: tqdm>=4.61.2; extra == 'extra'
Provides-Extra: test
Requires-Dist: pytest~=7.2.2; extra == 'test'
